ElementaryLogicGates.v
//------------------------------------------------------------------------------
// Elementary Logic Gates
// Each gate only uses the gates defined before in its implementation.
//------------------------------------------------------------------------------

module NAND (
    output Y,
    input A, B
);

    wire T;
    and(T, A, B);
    not(Y, T);

endmodule

module NOT (
    output Y,
    input A
);

    NAND nand_gate(Y, A, A);

endmodule

module AND (
    output Y,
    input A, B
);

    wire T;
    NAND nand_gate(T, A, B);
    NOT not_gate(Y, T);

endmodule

module OR (
    output Y,
    input A, B
);

    wire notA, notB;
    NOT not_gate_1(notA, A);
    NOT not_gate_2(notB, B);
    NAND nand_gate(Y, notA, notB);

endmodule

module XOR (
    output Y,
    input A, B
);

    wire T1, T2, T3;
    NAND nand_gate_1(T1, A, B);
    NAND nand_gate_2(T2, T1, A);
    NAND nand_gate_3(T3, T1, B);
    NAND nand_gate_4(Y, T2, T3);

endmodule

module MUX (
    output Y,
    input S, A, B
);

    wire not_S, and_nSA, and_SB;
    
    NOT not_gate(not_S, S);

    AND and_gate_1(and_nSA, not_S, A);
    AND and_gate_2(and_SB, S, B);
    OR or_gate(Y, and_nSA, and_SB);

endmodule

module DMUX (
    output X, Y,
    input S, A
);

    wire not_S;
    NOT not_gate(not_S, S);
    AND and_gate_1(X, not_S, A);
    AND and_gate_2(Y, S, A);

endmodule

module NOT16 (Y, A);

    input [15:0] A;
    output [15:0] Y;

    genvar i;
    generate
        for (i = 0; i < 16; i = i + 1) begin
            NOT not_gate(Y[i], A[i]);
        end
    endgenerate

endmodule

module AND16 (Y, A, B);

    input [15:0] A;
    input [15:0] B;
    output [15:0] Y;

    genvar i;
    generate
        for (i = 0; i < 16; i = i + 1) begin
            AND and_gate(Y[i], A[i], B[i]);
        end
    endgenerate

endmodule

module OR16 (Y, A, B);

    input [15:0] A;
    input [15:0] B;
    output [15:0] Y;

    genvar i;
    generate
        for (i = 0; i < 16; i = i + 1) begin
            OR or_gate(Y[i], A[i], B[i]);
        end
    endgenerate

endmodule

module MUX16 (Y, S, A, B);

    input S;
    input [15:0] A;
    input [15:0] B;
    output [15:0] Y;

    wire not_S;
    wire [15:0] and_nSA;
    wire [15:0] and_SB;

    NOT not_gate(not_S, S);

    genvar i;
    generate
        for (i = 0; i < 16; i = i + 1) begin
            AND and_gate_1(and_nSA[i], not_S, A[i]);
            AND and_gate_2(and_SB[i], S, B[i]);
        end
    endgenerate

    OR16 or_gate(Y, and_nSA, and_SB);

endmodule

module OR8WAY (Y, A);

    input [7:0] A;
    output Y;

    wire or_01, or_23, or_45, or_67, or_0123, or_4567;
    OR or_gate_1(or_01, A[0], A[1]);
    OR or_gate_2(or_23, A[2], A[3]);
    OR or_gate_3(or_45, A[4], A[5]);
    OR or_gate_4(or_67, A[6], A[7]);
    
    OR or_gate_5(or_0123, or_01, or_23);
    OR or_gate_6(or_4567, or_45, or_67);

    OR or_gate_7(Y, or_0123, or_4567);

endmodule

module MUX4WAY16 (Y, S, A, B, C, D);

    input [1:0] S;
    input [15:0] A, B, C, D;
    output [15:0] Y;

    wire [15:0] T1, T2;

    MUX16 mux16_gate_1(T1, S[0], A, B);
    MUX16 mux16_gate_2(T2, S[0], C, D);
    MUX16 mux16_gate_3(Y, S[1], T1, T2);

endmodule

module MUX8WAY16 (Y, S, A, B, C, D, E, F, G, H);

    input [2:0] S;
    input [15:0] A, B, C, D, E, F, G, H;
    output [15:0] Y;

    wire [15:0] T1, T2;

    MUX4WAY16 mux4way16_gate_1(T1, S[1:0], A, B, C, D);
    MUX4WAY16 mux4way16_gate_2(T2, S[1:0], E, F, G, H);
    MUX16 mux16_gate(Y, S[2], T1, T2);

endmodule

module DMUX4WAY (Y0, Y1, Y2, Y3, S, A);

    input [1:0] S;
    input A;
    output Y0, Y1, Y2, Y3;

    wire T1, T2;

    DMUX dmux_gate_1(T1, T2, S[1], A);
    DMUX dmux_gate_2(Y0, Y1, S[0], T1);
    DMUX dmux_gate_3(Y2, Y3, S[0], T2);

endmodule

module DMUX8WAY (Y0, Y1, Y2, Y3, Y4, Y5, Y6, Y7, S, A);

    input [2:0] S;
    input A;
    output Y0, Y1, Y2, Y3, Y4, Y5, Y6, Y7;

    wire T1, T2;

    DMUX dmux_gate(T1, T2, S[2], A);
    DMUX4WAY dmux4way_gate_1(Y0, Y1, Y2, Y3, S[1:0], T1);
    DMUX4WAY dmux4way_gate_2(Y4, Y5, Y6, Y7, S[1:0], T2);

endmodule

LogicGatesTestBenches/mux_tb.v
`include "../ElementaryLogicGates.v"

module MUX_tb;

    reg S, A, B;
    wire Y;

    MUX mux_gate(Y, S, A, B);

    initial begin
            S = 0; A = 0; B = 0;
        #1  S = 0; A = 0; B = 1;
        #1  S = 0; A = 1; B = 0;
        #1  S = 0; A = 1; B = 1;
        #1  S = 1; A = 0; B = 0;
        #1  S = 1; A = 0; B = 1;
        #1  S = 1; A = 1; B = 0;
        #1  S = 1; A = 1; B = 1;
    end

    initial begin
        $monitor ("%t | S = %d | A = %d | B = %d | Y = %d", $time, S, A, B, Y);
        $dumpfile("./DumpFiles/mux_dump.vcd");
        $dumpvars();
    end

endmodule

LogicGatesTestBenches/DumpFiles/mux_dump.vcd
$date
	Thu Oct 28 14:00:33 2021
$end
$version
	Icarus Verilog
$end
$timescale
	1s
$end
$scope module MUX_tb $end
$var wire 1 ! Y $end
$var reg 1 " A $end
$var reg 1 # B $end
$var reg 1 $ S $end
$scope module mux_gate $end
$var wire 1 " A $end
$var wire 1 # B $end
$var wire 1 $ S $end
$var wire 1 % not_S $end
$var wire 1 & and_nSA $end
$var wire 1 ' and_SB $end
$var wire 1 ! Y $end
$scope module and_gate_1 $end
$var wire 1 " B $end
$var wire 1 & Y $end
$var wire 1 ( T $end
$var wire 1 % A $end
$scope module nand_gate $end
$var wire 1 " B $end
$var wire 1 ) T $end
$var wire 1 ( Y $end
$var wire 1 % A $end
$upscope $end
$scope module not_gate $end
$var wire 1 ( A $end
$var wire 1 & Y $end
$scope module nand_gate $end
$var wire 1 ( A $end
$var wire 1 ( B $end
$var wire 1 * T $end
$var wire 1 & Y $end
$upscope $end
$upscope $end
$upscope $end
$scope module and_gate_2 $end
$var wire 1 $ A $end
$var wire 1 # B $end
$var wire 1 ' Y $end
$var wire 1 + T $end
$scope module nand_gate $end
$var wire 1 $ A $end
$var wire 1 # B $end
$var wire 1 , T $end
$var wire 1 + Y $end
$upscope $end
$scope module not_gate $end
$var wire 1 + A $end
$var wire 1 ' Y $end
$scope module nand_gate $end
$var wire 1 + A $end
$var wire 1 + B $end
$var wire 1 - T $end
$var wire 1 ' Y $end
$upscope $end
$upscope $end
$upscope $end
$scope module not_gate $end
$var wire 1 $ A $end
$var wire 1 % Y $end
$scope module nand_gate $end
$var wire 1 $ A $end
$var wire 1 $ B $end
$var wire 1 . T $end
$var wire 1 % Y $end
$upscope $end
$upscope $end
$scope module or_gate $end
$var wire 1 & A $end
$var wire 1 ' B $end
$var wire 1 / notB $end
$var wire 1 0 notA $end
$var wire 1 ! Y $end
$scope module nand_gate $end
$var wire 1 1 T $end
$var wire 1 ! Y $end
$var wire 1 / B $end
$var wire 1 0 A $end
$upscope $end
$scope module not_gate_1 $end
$var wire 1 & A $end
$var wire 1 0 Y $end
$scope module nand_gate $end
$var wire 1 & A $end
$var wire 1 & B $end
$var wire 1 2 T $end
$var wire 1 0 Y $end
$upscope $end
$upscope $end
$scope module not_gate_2 $end
$var wire 1 ' A $end
$var wire 1 / Y $end
$scope module nand_gate $end
$var wire 1 ' A $end
$var wire 1 ' B $end
$var wire 1 3 T $end
$var wire 1 / Y $end
$upscope $end
$upscope $end
$upscope $end
$upscope $end
$upscope $end
$enddefinitions $end
#0
$dumpvars
03
02
11
10
1/
0.
1-
0,
1+
1*
0)
1(
0'
0&
1%
0$
0#
0"
0!
$end
#1
1#
#2
1!
01
00
12
1&
0*
0(
1)
0#
1"
#3
1#
#4
0!
11
10
02
0&
1*
1(
0%
0)
1.
0#
0"
1$
#5
1!
01
0/
13
1'
0-
0+
1,
1#
#6
0!
11
1/
03
0'
1-
1+
0,
0#
1"
#7
1!
01
0/
13
1'
0-
0+
1,
1#
